cmake_build_extension/__init__.py
cmake_build_extension/build_ext_option.py
cmake_build_extension/build_extension.py
cmake_build_extension/cmake_extension.py
cmake_build_extension/sdist_command.py
cmake_build_extension-0.6.1.dist-info/LICENSE
cmake_build_extension-0.6.1.dist-info/METADATA
cmake_build_extension-0.6.1.dist-info/WHEEL
cmake_build_extension-0.6.1.dist-info/top_level.txt
cmake_build_extension-0.6.1.dist-info/RECORD
